chalice_spec_pr07/__init__.py
chalice_spec_pr07/chalice.py
chalice_spec_pr07/docs.py
chalice_spec_pr07/pydantic.py
chalice_spec_pr07-0.1.5.dist-info/LICENSE
chalice_spec_pr07-0.1.5.dist-info/METADATA
chalice_spec_pr07-0.1.5.dist-info/WHEEL
chalice_spec_pr07-0.1.5.dist-info/RECORD
