Metadata-Version: 2.1
Name: chalice-spec-pr07
Version: 0.1.5
Summary: Chalice x APISpec x Pydantic plug-ins
Home-page: https://github.com/TestBoxLab/chalice-spec
License: MIT
Keywords: Chalice,AWS,APIspec,OpenAPI,Pydantic
Author: Jake Wood
Author-email: jake@testbox.com
Requires-Python: >=3.7,<4.0
Classifier: License :: OSI Approved :: MIT License
Classifier: Programming Language :: Python :: 3
Classifier: Programming Language :: Python :: 3.7
Classifier: Programming Language :: Python :: 3.8
Classifier: Programming Language :: Python :: 3.9
Classifier: Programming Language :: Python :: 3.10
Classifier: Programming Language :: Python :: 3.11
Requires-Dist: apispec (>=5.2.2,<6.0.0)
Project-URL: Repository, https://github.com/TestBoxLab/chalice-spec
